MANIFEST.in
README.rst
setup.py
pysi/__init__.py
pysi/config.py
pysi/decorators.py
pysi/exceptions.py
pysi/middlewares.py
pysi/multidict.py
pysi/routing.py
pysi/signal.py
pysi/static.py
pysi/template.py
pysi/util.py
pysi/wsgi.py
pysi.egg-info/PKG-INFO
pysi.egg-info/SOURCES.txt
pysi.egg-info/dependency_links.txt
pysi.egg-info/requires.txt
pysi.egg-info/top_level.txt