Metadata-Version: 1.1
Name: pysi
Version: 0.17.1
Summary: Fast and simple micro web framework
Home-page: http://bitbucket.org/imbolc/pysi/
Author: Imbolc
Author-email: imbolc@imbolc.name
License: MIT
Keywords: web framework
Platform: UNKNOWN
Classifier: Development Status :: 4 - Beta
Classifier: Environment :: Web Environment
Classifier: Intended Audience :: Developers
Classifier: License :: OSI Approved :: BSD License
Classifier: Operating System :: OS Independent
Classifier: Programming Language :: Python
Classifier: Topic :: Software Development :: Libraries :: Application Frameworks
Classifier: Topic :: Software Development :: Libraries :: Python Modules
